xcnt_apispec_utils-2022.0.3-py3.10-nspkg.pth
xcnt/apispec/utils/__init__.py
xcnt/apispec/utils/flasgger_api_spec.py
xcnt/apispec/utils/flask_plugin.py
xcnt/apispec/utils/search_param_plugin.py
xcnt/apispec/utils/swagger.py
xcnt/apispec/utils/marshmallow_plugin/__init__.py
xcnt/apispec/utils/marshmallow_plugin/marshmallow_plugin.py
xcnt/apispec/utils/test/__init__.py
xcnt/apispec/utils/test/test_apispec_plugins.py
xcnt_apispec_utils-2022.0.3.dist-info/METADATA
xcnt_apispec_utils-2022.0.3.dist-info/WHEEL
xcnt_apispec_utils-2022.0.3.dist-info/namespace_packages.txt
xcnt_apispec_utils-2022.0.3.dist-info/top_level.txt
xcnt_apispec_utils-2022.0.3.dist-info/RECORD
